<?xml version="1.0" encoding="UTF-8" standalone="no"?>
<AudioModification.xml><AudioModification><Name>PVZ</Name><ExternalEvent><Name>Play_Autopilot</Name><Container><Name>Voice</Name><ExternalId>VAutopilot</ExternalId><Path><StateList><State><Name>Autopilot</Name><Value>Checkpoint</Value></State></StateList><FilesList><File><Name>crazydave1.wem</Name></File><File><Name>crazydave2.wem</Name></File><File><Name>crazydave3.wem</Name></File><File><Name>crazydave4.wem</Name></File><File><Name>crazydave5.wem</Name></File><File><Name>crazydave6.wem</Name></File><File><Name>crazydave7.wem</Name></File><File><Name>crazydave8.wem</Name></File><File><Name>crazydave9.wem</Name></File></FilesList></Path><Path><StateList><State><Name>Autopilot</Name><Value>End</Value></State></StateList><FilesList><File><Name>crazydave1.wem</Name></File><File><Name>crazydave2.wem</Name></File><File><Name>crazydave3.wem</Name></File><File><Name>crazydave4.wem</Name></File><File><Name>crazydave5.wem</Name></File><File><Name>crazydave6.wem</Name></File><File><Name>crazydave7.wem</Name></File><File><Name>crazydave8.wem</Name></File><File><Name>crazydave9.wem</Name></File></FilesList></Path><Path><StateList><State><Name>Autopilot</Name><Value>Off</Value></State></StateList><FilesList><File><Name>crazydave1.wem</Name></File><File><Name>crazydave2.wem</Name></File><File><Name>crazydave3.wem</Name></File><File><Name>crazydave4.wem</Name></File><File><Name>crazydave5.wem</Name></File><File><Name>crazydave6.wem</Name></File><File><Name>crazydave7.wem</Name></File><File><Name>crazydave8.wem</Name></File><File><Name>crazydave9.wem</Name></File></FilesList></Path><Path><StateList><State><Name>Autopilot</Name><Value>On</Value></State></StateList><FilesList><File><Name>crazydave1.wem</Name></File><File><Name>crazydave2.wem</Name></File><File><Name>crazydave3.wem</Name></File><File><Name>crazydave4.wem</Name></File><File><Name>crazydave5.wem</Name></File><File><Name>crazydave6.wem</Name></File><File><Name>crazydave7.wem</Name></File><File><Name>crazydave8.wem</Name></File><File><Name>crazydave9.wem</Name></File></FilesList></Path></Container></ExternalEvent><ExternalEvent><Name>Play_Avatar_Damage</Name><Container><Name>Voice</Name><ExternalId>VAvatar_Damage</ExternalId><Path><StateList><State><Name>Debuff</Name><Value>CriticalFlooding</Value></State></StateList><FilesList><File><Name>zobiesplash.wem</Name></File><File><Name>fume.wem</Name></File></FilesList></Path></Container></ExternalEvent><ExternalEvent><Name>Play_Detection_enemy</Name><Container><Name>Voice</Name><ExternalId>VDetection_enemy</ExternalId><Path><StateList><State><Name>DetectionEnemy</Name><Value>AirCarrier</Value></State></StateList><FilesList><File><Name>Silence.wem</Name></File></FilesList></Path><Path><StateList><State><Name>DetectionEnemy</Name><Value>Battleship</Value></State></StateList><FilesList><File><Name>Silence.wem</Name></File></FilesList></Path><Path><StateList><State><Name>DetectionEnemy</Name><Value>Cruiser</Value></State></StateList><FilesList><File><Name>Silence.wem</Name></File></FilesList></Path><Path><StateList><State><Name>DetectionEnemy</Name><Value>Destroyer</Value></State></StateList><FilesList><File><Name>Silence.wem</Name></File></FilesList></Path><Path><StateList><State><Name>DetectionEnemy</Name><Value>Multi</Value></State></StateList><FilesList><File><Name>squash_hmm.wem</Name></File><File><Name>squash_hmm2.wem</Name></File></FilesList></Path></Container></ExternalEvent><ExternalEvent><Name>Play_DominationStatus</Name><Container><Name>Voice</Name><ExternalId>VDominationStatus</ExternalId><Path><StateList><State><Name>Domination</Name><Value>D_Ally</Value></State></StateList><FilesList><File><Name>jackinthebox.wem</Name></File></FilesList></Path><Path><StateList><State><Name>Domination</Name><Value>D_Enemy</Value></State></StateList><FilesList><File><Name>imp.wem</Name></File><File><Name>imp2.wem</Name></File></FilesList></Path><Path><StateList><State><Name>Domination</Name><Value>W_Ally</Value></State></StateList><FilesList><File><Name>winmusic.wem</Name></File></FilesList></Path><Path><StateList><State><Name>Domination</Name><Value>W_Enemy</Value></State></StateList><FilesList><File><Name>losemusic.wem</Name></File></FilesList></Path></Container></ExternalEvent><ExternalEvent><Name>Play_DoubleKill</Name><Container><Name>Voice</Name><ExternalId>VDoubleKill</ExternalId><Path><StateList></StateList><FilesList><File><Name>polevault.wem</Name></File></FilesList></Path></Container></ExternalEvent><ExternalEvent><Name>Play_Fire</Name><Container><Name>Voice</Name><ExternalId>VFire</ExternalId><Path><StateList><State><Name>isPlayer</Name><Value>True</Value></State></StateList><FilesList><File><Name>crazydave1.wem</Name></File><File><Name>crazydave2.wem</Name></File><File><Name>crazydave3.wem</Name></File><File><Name>crazydave4.wem</Name></File><File><Name>crazydave5.wem</Name></File><File><Name>crazydave6.wem</Name></File><File><Name>crazydave7.wem</Name></File><File><Name>crazydave8.wem</Name></File><File><Name>crazydave9.wem</Name></File></FilesList></Path></Container></ExternalEvent><ExternalEvent><Name>Play_FirstKill</Name><Container><Name>Voice</Name><ExternalId>VFirstKill</ExternalId><Path><StateList></StateList><FilesList><File><Name>prize.wem</Name></File></FilesList></Path></Container></ExternalEvent><ExternalEvent><Name>Play_Frags</Name><Container><Name>Voice</Name><ExternalId>VFrags</ExternalId><Path><StateList><State><Name>Frag_Type</Name><Value>AirCarrier</Value></State><State><Name>isPlayer</Name><Value>False</Value></State></StateList><FilesList><File><Name>01brains.wem</Name></File><File><Name>02brains.wem</Name></File><File><Name>03brains.wem</Name></File><File><Name>04brains.wem</Name></File><File><Name>05brains.wem</Name></File><File><Name>06brains.wem</Name></File><File><Name>07brains.wem</Name></File><File><Name>08brains.wem</Name></File><File><Name>09brains.wem</Name></File><File><Name>0abrains.wem</Name></File><File><Name>0bbrains.wem</Name></File><File><Name>0cbrains.wem</Name></File></FilesList></Path><Path><StateList><State><Name>Frag_Type</Name><Value>AirCarrier</Value></State><State><Name>isPlayer</Name><Value>True</Value></State></StateList><FilesList><File><Name>Silence.wem</Name></File></FilesList></Path><Path><StateList><State><Name>Frag_Type</Name><Value>Battleship</Value></State><State><Name>isPlayer</Name><Value>False</Value></State></StateList><FilesList><File><Name>brains01.wem</Name></File><File><Name>brains02.wem</Name></File><File><Name>brains03.wem</Name></File><File><Name>brains04.wem</Name></File><File><Name>brains05.wem</Name></File><File><Name>brains06.wem</Name></File><File><Name>brains07.wem</Name></File><File><Name>brains08.wem</Name></File><File><Name>brains09.wem</Name></File><File><Name>brains0a.wem</Name></File><File><Name>brains0b.wem</Name></File><File><Name>brains0c.wem</Name></File></FilesList></Path><Path><StateList><State><Name>Frag_Type</Name><Value>Battleship</Value></State><State><Name>isPlayer</Name><Value>True</Value></State></StateList><FilesList><File><Name>Silence.wem</Name></File></FilesList></Path><Path><StateList><State><Name>Frag_Type</Name><Value>Cruiser</Value></State><State><Name>isPlayer</Name><Value>False</Value></State></StateList><FilesList><File><Name>brains01.wem</Name></File><File><Name>brains02.wem</Name></File><File><Name>brains03.wem</Name></File><File><Name>brains04.wem</Name></File><File><Name>brains05.wem</Name></File><File><Name>brains06.wem</Name></File><File><Name>brains07.wem</Name></File><File><Name>brains08.wem</Name></File><File><Name>brains09.wem</Name></File><File><Name>brains0a.wem</Name></File><File><Name>brains0b.wem</Name></File><File><Name>brains0c.wem</Name></File></FilesList></Path><Path><StateList><State><Name>Frag_Type</Name><Value>Cruiser</Value></State><State><Name>isPlayer</Name><Value>True</Value></State></StateList><FilesList><File><Name>Silence.wem</Name></File></FilesList></Path><Path><StateList><State><Name>Frag_Type</Name><Value>Destroyer</Value></State><State><Name>isPlayer</Name><Value>False</Value></State></StateList><FilesList><File><Name>brains01.wem</Name></File><File><Name>brains02.wem</Name></File><File><Name>brains03.wem</Name></File><File><Name>brains04.wem</Name></File><File><Name>brains05.wem</Name></File><File><Name>brains06.wem</Name></File><File><Name>brains07.wem</Name></File><File><Name>brains08.wem</Name></File><File><Name>brains09.wem</Name></File><File><Name>brains0a.wem</Name></File><File><Name>brains0b.wem</Name></File><File><Name>brains0c.wem</Name></File></FilesList></Path><Path><StateList><State><Name>Frag_Type</Name><Value>Destroyer</Value></State><State><Name>isPlayer</Name><Value>True</Value></State></StateList><FilesList><File><Name>Silence.wem</Name></File></FilesList></Path></Container></ExternalEvent><ExternalEvent><Name>Play_FriendlyHit</Name><Container><Name>Voice</Name><ExternalId>VFriendlyHit</ExternalId><Path><StateList></StateList><FilesList><File><Name>crazydave1.wem</Name></File><File><Name>crazydave2.wem</Name></File><File><Name>crazydave3.wem</Name></File><File><Name>crazydave4.wem</Name></File><File><Name>crazydave5.wem</Name></File><File><Name>crazydave6.wem</Name></File><File><Name>crazydave7.wem</Name></File><File><Name>crazydave8.wem</Name></File><File><Name>crazydave9.wem</Name></File></FilesList></Path></Container></ExternalEvent><ExternalEvent><Name>Play_GoodHit</Name><Container><Name>Voice</Name><ExternalId>VGoodHit</ExternalId><Path><StateList></StateList><FilesList><File><Name>crazydaveE1.wem</Name></File><File><Name>crazydaveE2.wem</Name></File><File><Name>crazydaveE3.wem</Name></File></FilesList></Path></Container></ExternalEvent><ExternalEvent><Name>Play_Help</Name><Container><Name>Voice</Name><ExternalId>VHelp</ExternalId><Path><StateList><State><Name>HelpType</Name><Value>AirDefenseDisp</Value></State></StateList><FilesList><File><Name>bungee_scream.wem</Name></File><File><Name>bungee_scream2.wem</Name></File><File><Name>bungee_scream3.wem</Name></File></FilesList></Path><Path><StateList><State><Name>HelpType</Name><Value>Engine</Value></State></StateList><FilesList><File><Name>zamboni.wem</Name></File></FilesList></Path><Path><StateList><State><Name>HelpType</Name><Value>Fighter</Value></State></StateList><FilesList><File><Name>coblandch.wem</Name></File></FilesList></Path><Path><StateList><State><Name>HelpType</Name><Value>Scout</Value></State></StateList><FilesList><File><Name>cablaunch.wem</Name></File></FilesList></Path><Path><StateList><State><Name>HelpType</Name><Value>Smoke</Value></State></StateList><FilesList><File><Name>floop.wem</Name></File></FilesList></Path></Container></ExternalEvent><ExternalEvent><Name>Play_Help_End</Name><Container><Name>Voice</Name><ExternalId>VHelp_End</ExternalId><Path><StateList><State><Name>HelpType</Name><Value>AirDefenseDisp</Value></State></StateList><FilesList><File><Name>lightfill.wem</Name></File></FilesList></Path><Path><StateList><State><Name>HelpType</Name><Value>CrashCrew</Value></State></StateList><FilesList><File><Name>blover.wem</Name></File></FilesList></Path><Path><StateList><State><Name>HelpType</Name><Value>Engine</Value></State></StateList><FilesList><File><Name>lawnmower.wem</Name></File></FilesList></Path><Path><StateList><State><Name>HelpType</Name><Value>Smoke</Value></State></StateList><FilesList><File><Name>Silence.wem</Name></File></FilesList></Path></Container></ExternalEvent><ExternalEvent><Name>Play_Last_Hope</Name><Container><Name>Voice</Name><ExternalId>VLast_Hope</ExternalId><Path><StateList></StateList><FilesList><File><Name>finalwave.wem</Name></File></FilesList></Path></Container></ExternalEvent><ExternalEvent><Name>Play_LetsBatlle</Name><Container><Name>Voice</Name><ExternalId>VLetsBatlle</ExternalId><Path><StateList></StateList><FilesList><File><Name>readysetplant.wem</Name></File><File><Name>siren.wem</Name></File><File><Name>awooga.wem</Name></File></FilesList></Path></Container></ExternalEvent><ExternalEvent><Name>Play_Pilots_ID</Name><Container><Name>Voice</Name><ExternalId>VPilots_ID</ExternalId><Path><StateList><State><Name>Plane_Type</Name><Value>Bomber</Value></State><State><Name>PlaneID</Name><Value>id1</Value></State></StateList><FilesList><File><Name>crazydaveshort1.wem</Name></File><File><Name>crazydaveshort2.wem</Name></File><File><Name>crazydaveshort3.wem</Name></File></FilesList></Path><Path><StateList><State><Name>Plane_Type</Name><Value>Bomber</Value></State><State><Name>PlaneID</Name><Value>id2</Value></State></StateList><FilesList><File><Name>crazydaveshort1.wem</Name></File><File><Name>crazydaveshort2.wem</Name></File><File><Name>crazydaveshort3.wem</Name></File></FilesList></Path><Path><StateList><State><Name>Plane_Type</Name><Value>Bomber</Value></State><State><Name>PlaneID</Name><Value>id3</Value></State></StateList><FilesList><File><Name>crazydaveshort1.wem</Name></File><File><Name>crazydaveshort2.wem</Name></File><File><Name>crazydaveshort3.wem</Name></File></FilesList></Path><Path><StateList><State><Name>Plane_Type</Name><Value>Bomber</Value></State><State><Name>PlaneID</Name><Value>id4</Value></State></StateList><FilesList><File><Name>crazydaveshort1.wem</Name></File><File><Name>crazydaveshort2.wem</Name></File><File><Name>crazydaveshort3.wem</Name></File></FilesList></Path><Path><StateList><State><Name>Plane_Type</Name><Value>Bomber</Value></State><State><Name>PlaneID</Name><Value>id5</Value></State></StateList><FilesList><File><Name>crazydaveshort1.wem</Name></File><File><Name>crazydaveshort2.wem</Name></File><File><Name>crazydaveshort3.wem</Name></File></FilesList></Path><Path><StateList><State><Name>Plane_Type</Name><Value>Bomber</Value></State><State><Name>PlaneID</Name><Value>id6</Value></State></StateList><FilesList><File><Name>crazydaveshort1.wem</Name></File><File><Name>crazydaveshort2.wem</Name></File><File><Name>crazydaveshort3.wem</Name></File></FilesList></Path><Path><StateList><State><Name>Plane_Type</Name><Value>Bomber</Value></State><State><Name>PlaneID</Name><Value>id7</Value></State></StateList><FilesList><File><Name>crazydaveshort1.wem</Name></File><File><Name>crazydaveshort2.wem</Name></File><File><Name>crazydaveshort3.wem</Name></File></FilesList></Path><Path><StateList><State><Name>Plane_Type</Name><Value>Bomber</Value></State><State><Name>PlaneID</Name><Value>id8</Value></State></StateList><FilesList><File><Name>crazydaveshort1.wem</Name></File><File><Name>crazydaveshort2.wem</Name></File><File><Name>crazydaveshort3.wem</Name></File></FilesList></Path><Path><StateList><State><Name>Plane_Type</Name><Value>Bomber</Value></State><State><Name>PlaneID</Name><Value>id9</Value></State></StateList><FilesList><File><Name>crazydaveshort1.wem</Name></File><File><Name>crazydaveshort2.wem</Name></File><File><Name>crazydaveshort3.wem</Name></File></FilesList></Path><Path><StateList><State><Name>Plane_Type</Name><Value>Fighter</Value></State><State><Name>PlaneID</Name><Value>id1</Value></State></StateList><FilesList><File><Name>crazydaveshort1.wem</Name></File><File><Name>crazydaveshort2.wem</Name></File><File><Name>crazydaveshort3.wem</Name></File></FilesList></Path><Path><StateList><State><Name>Plane_Type</Name><Value>Fighter</Value></State><State><Name>PlaneID</Name><Value>id2</Value></State></StateList><FilesList><File><Name>crazydaveshort1.wem</Name></File><File><Name>crazydaveshort2.wem</Name></File><File><Name>crazydaveshort3.wem</Name></File></FilesList></Path><Path><StateList><State><Name>Plane_Type</Name><Value>Fighter</Value></State><State><Name>PlaneID</Name><Value>id3</Value></State></StateList><FilesList><File><Name>crazydaveshort1.wem</Name></File><File><Name>crazydaveshort2.wem</Name></File><File><Name>crazydaveshort3.wem</Name></File></FilesList></Path><Path><StateList><State><Name>Plane_Type</Name><Value>Fighter</Value></State><State><Name>PlaneID</Name><Value>id4</Value></State></StateList><FilesList><File><Name>crazydaveshort1.wem</Name></File><File><Name>crazydaveshort2.wem</Name></File><File><Name>crazydaveshort3.wem</Name></File></FilesList></Path><Path><StateList><State><Name>Plane_Type</Name><Value>Fighter</Value></State><State><Name>PlaneID</Name><Value>id5</Value></State></StateList><FilesList><File><Name>crazydaveshort1.wem</Name></File><File><Name>crazydaveshort2.wem</Name></File><File><Name>crazydaveshort3.wem</Name></File></FilesList></Path><Path><StateList><State><Name>Plane_Type</Name><Value>Fighter</Value></State><State><Name>PlaneID</Name><Value>id6</Value></State></StateList><FilesList><File><Name>crazydaveshort1.wem</Name></File><File><Name>crazydaveshort2.wem</Name></File><File><Name>crazydaveshort3.wem</Name></File></FilesList></Path><Path><StateList><State><Name>Plane_Type</Name><Value>Fighter</Value></State><State><Name>PlaneID</Name><Value>id7</Value></State></StateList><FilesList><File><Name>crazydaveshort1.wem</Name></File><File><Name>crazydaveshort2.wem</Name></File><File><Name>crazydaveshort3.wem</Name></File></FilesList></Path><Path><StateList><State><Name>Plane_Type</Name><Value>Fighter</Value></State><State><Name>PlaneID</Name><Value>id8</Value></State></StateList><FilesList><File><Name>crazydaveshort1.wem</Name></File><File><Name>crazydaveshort2.wem</Name></File><File><Name>crazydaveshort3.wem</Name></File></FilesList></Path><Path><StateList><State><Name>Plane_Type</Name><Value>Fighter</Value></State><State><Name>PlaneID</Name><Value>id9</Value></State></StateList><FilesList><File><Name>crazydaveshort1.wem</Name></File><File><Name>crazydaveshort2.wem</Name></File><File><Name>crazydaveshort3.wem</Name></File></FilesList></Path><Path><StateList><State><Name>Plane_Type</Name><Value>Torpedo</Value></State><State><Name>PlaneID</Name><Value>id1</Value></State></StateList><FilesList><File><Name>crazydaveshort1.wem</Name></File><File><Name>crazydaveshort2.wem</Name></File><File><Name>crazydaveshort3.wem</Name></File></FilesList></Path><Path><StateList><State><Name>Plane_Type</Name><Value>Torpedo</Value></State><State><Name>PlaneID</Name><Value>id2</Value></State></StateList><FilesList><File><Name>crazydaveshort1.wem</Name></File><File><Name>crazydaveshort2.wem</Name></File><File><Name>crazydaveshort3.wem</Name></File></FilesList></Path><Path><StateList><State><Name>Plane_Type</Name><Value>Torpedo</Value></State><State><Name>PlaneID</Name><Value>id3</Value></State></StateList><FilesList><File><Name>crazydaveshort1.wem</Name></File><File><Name>crazydaveshort2.wem</Name></File><File><Name>crazydaveshort3.wem</Name></File></FilesList></Path><Path><StateList><State><Name>Plane_Type</Name><Value>Torpedo</Value></State><State><Name>PlaneID</Name><Value>id4</Value></State></StateList><FilesList><File><Name>crazydaveshort1.wem</Name></File><File><Name>crazydaveshort2.wem</Name></File><File><Name>crazydaveshort3.wem</Name></File></FilesList></Path><Path><StateList><State><Name>Plane_Type</Name><Value>Torpedo</Value></State><State><Name>PlaneID</Name><Value>id5</Value></State></StateList><FilesList><File><Name>crazydaveshort1.wem</Name></File><File><Name>crazydaveshort2.wem</Name></File><File><Name>crazydaveshort3.wem</Name></File></FilesList></Path><Path><StateList><State><Name>Plane_Type</Name><Value>Torpedo</Value></State><State><Name>PlaneID</Name><Value>id6</Value></State></StateList><FilesList><File><Name>crazydaveshort1.wem</Name></File><File><Name>crazydaveshort2.wem</Name></File><File><Name>crazydaveshort3.wem</Name></File></FilesList></Path><Path><StateList><State><Name>Plane_Type</Name><Value>Torpedo</Value></State><State><Name>PlaneID</Name><Value>id7</Value></State></StateList><FilesList><File><Name>crazydaveshort1.wem</Name></File><File><Name>crazydaveshort2.wem</Name></File><File><Name>crazydaveshort3.wem</Name></File></FilesList></Path><Path><StateList><State><Name>Plane_Type</Name><Value>Torpedo</Value></State><State><Name>PlaneID</Name><Value>id8</Value></State></StateList><FilesList><File><Name>crazydaveshort1.wem</Name></File><File><Name>crazydaveshort2.wem</Name></File><File><Name>crazydaveshort3.wem</Name></File></FilesList></Path><Path><StateList><State><Name>Plane_Type</Name><Value>Torpedo</Value></State><State><Name>PlaneID</Name><Value>id9</Value></State></StateList><FilesList><File><Name>crazydaveshort1.wem</Name></File><File><Name>crazydaveshort2.wem</Name></File><File><Name>crazydaveshort3.wem</Name></File></FilesList></Path></Container></ExternalEvent><ExternalEvent><Name>Play_Pilots_Status</Name><Container><Name>Voice</Name><ExternalId>VPilots_Status</ExternalId><Path><StateList><State><Name>PlaneStatus</Name><Value>Airborne</Value></State><State><Name>Plane_Type</Name><Value>Bomber</Value></State></StateList><FilesList><File><Name>coblaunch1.wem</Name></File><File><Name>coblaunch2.wem</Name></File><File><Name>coblaunch3.wem</Name></File><File><Name>coblaunch4.wem</Name></File><File><Name>coblaunch5.wem</Name></File><File><Name>coblaunch6.wem</Name></File></FilesList></Path><Path><StateList><State><Name>PlaneStatus</Name><Value>Airborne</Value></State><State><Name>Plane_Type</Name><Value>Fighter</Value></State></StateList><FilesList><File><Name>coblaunch1.wem</Name></File><File><Name>coblaunch2.wem</Name></File><File><Name>coblaunch3.wem</Name></File><File><Name>coblaunch4.wem</Name></File><File><Name>coblaunch5.wem</Name></File><File><Name>coblaunch6.wem</Name></File></FilesList></Path><Path><StateList><State><Name>PlaneStatus</Name><Value>Airborne</Value></State><State><Name>Plane_Type</Name><Value>Torpedo</Value></State></StateList><FilesList><File><Name>coblaunch1.wem</Name></File><File><Name>coblaunch2.wem</Name></File><File><Name>coblaunch3.wem</Name></File><File><Name>coblaunch4.wem</Name></File><File><Name>coblaunch5.wem</Name></File><File><Name>coblaunch6.wem</Name></File></FilesList></Path><Path><StateList><State><Name>PlaneStatus</Name><Value>AtPos</Value></State><State><Name>Plane_Type</Name><Value>Bomber</Value></State></StateList><FilesList><File><Name>lowgroan1.wem</Name></File><File><Name>lowgroan2.wem</Name></File><File><Name>lowgroan3.wem</Name></File><File><Name>lowgroan4.wem</Name></File><File><Name>lowgroan5.wem</Name></File><File><Name>lowgroan6.wem</Name></File><File><Name>lowgroan7.wem</Name></File><File><Name>lowgroan8.wem</Name></File><File><Name>lowgroan9.wem</Name></File><File><Name>lowgroana.wem</Name></File><File><Name>lowgroanb.wem</Name></File><File><Name>lowgroanc.wem</Name></File></FilesList></Path><Path><StateList><State><Name>PlaneStatus</Name><Value>AtPos</Value></State><State><Name>Plane_Type</Name><Value>Fighter</Value></State></StateList><FilesList><File><Name>lowgroan1.wem</Name></File><File><Name>lowgroan2.wem</Name></File><File><Name>lowgroan3.wem</Name></File><File><Name>lowgroan4.wem</Name></File><File><Name>lowgroan5.wem</Name></File><File><Name>lowgroan6.wem</Name></File><File><Name>lowgroan7.wem</Name></File><File><Name>lowgroan8.wem</Name></File><File><Name>lowgroan9.wem</Name></File><File><Name>lowgroana.wem</Name></File><File><Name>lowgroanb.wem</Name></File><File><Name>lowgroanc.wem</Name></File></FilesList></Path><Path><StateList><State><Name>PlaneStatus</Name><Value>AtPos</Value></State><State><Name>Plane_Type</Name><Value>Torpedo</Value></State></StateList><FilesList><File><Name>lowgroan1.wem</Name></File><File><Name>lowgroan2.wem</Name></File><File><Name>lowgroan3.wem</Name></File><File><Name>lowgroan4.wem</Name></File><File><Name>lowgroan5.wem</Name></File><File><Name>lowgroan6.wem</Name></File><File><Name>lowgroan7.wem</Name></File><File><Name>lowgroan8.wem</Name></File><File><Name>lowgroan9.wem</Name></File><File><Name>lowgroana.wem</Name></File><File><Name>lowgroanb.wem</Name></File><File><Name>lowgroanc.wem</Name></File></FilesList></Path><Path><StateList><State><Name>Plane_Type</Name><Value>Bomber</Value></State><State><Name>PlaneStatus</Name><Value>Destroy</Value></State></StateList><FilesList><File><Name>balloon_pop1.wem</Name></File><File><Name>balloon_pop2.wem</Name></File><File><Name>balloon_pop3.wem</Name></File><File><Name>balloon_pop4.wem</Name></File><File><Name>balloon_pop5.wem</Name></File><File><Name>balloon_pop6.wem</Name></File></FilesList></Path><Path><StateList><State><Name>Plane_Type</Name><Value>Bomber</Value></State><State><Name>PlaneStatus</Name><Value>Engage</Value></State></StateList><FilesList><File><Name>newspaperrarrgh1.wem</Name></File><File><Name>newspaperrarrgh2.wem</Name></File><File><Name>newspaperrarrgh3.wem</Name></File><File><Name>newspaperrarrgh4.wem</Name></File><File><Name>newspaperrarrgh5.wem</Name></File><File><Name>newspaperrarrgh6.wem</Name></File><File><Name>newspaperrarrgh7.wem</Name></File><File><Name>newspaperrarrgh8.wem</Name></File><File><Name>newspaperrarrgh9.wem</Name></File><File><Name>newspaperrarrgha.wem</Name></File><File><Name>newspaperrarrghb.wem</Name></File><File><Name>newspaperrarrghc.wem</Name></File></FilesList></Path><Path><StateList><State><Name>Plane_Type</Name><Value>Bomber</Value></State><State><Name>PlaneStatus</Name><Value>Land</Value></State></StateList><FilesList><File><Name>gargantuar_thump1.wem</Name></File><File><Name>gargantuar_thump2.wem</Name></File><File><Name>gargantuar_thump3.wem</Name></File><File><Name>gargantuar_thump4.wem</Name></File><File><Name>gargantuar_thump5.wem</Name></File><File><Name>gargantuar_thump6.wem</Name></File></FilesList></Path><Path><StateList><State><Name>Plane_Type</Name><Value>Bomber</Value></State><State><Name>PlaneStatus</Name><Value>Ready</Value></State></StateList><FilesList><File><Name>ballooninflate1.wem</Name></File><File><Name>ballooninflate2.wem</Name></File><File><Name>ballooninflate3.wem</Name></File><File><Name>ballooninflate4.wem</Name></File><File><Name>ballooninflate5.wem</Name></File><File><Name>ballooninflate6.wem</Name></File></FilesList></Path><Path><StateList><State><Name>Plane_Type</Name><Value>Bomber</Value></State><State><Name>PlaneStatus</Name><Value>TangoDown</Value></State></StateList><FilesList><File><Name>bowlingimpact1.wem</Name></File><File><Name>bowlingimpact2.wem</Name></File><File><Name>bowlingimpact3.wem</Name></File><File><Name>bowlingimpact4.wem</Name></File><File><Name>bowlingimpact5.wem</Name></File><File><Name>bowlingimpact6.wem</Name></File><File><Name>bowlingimpact7.wem</Name></File><File><Name>bowlingimpact8.wem</Name></File><File><Name>bowlingimpact9.wem</Name></File><File><Name>bowlingimpacta.wem</Name></File><File><Name>bowlingimpactb.wem</Name></File><File><Name>bowlingimpactc.wem</Name></File></FilesList></Path><Path><StateList><State><Name>Plane_Type</Name><Value>Bomber</Value></State><State><Name>PlaneStatus</Name><Value>UnderAttack</Value></State></StateList><FilesList><File><Name>jack_surprise1.wem</Name></File><File><Name>jack_surprise2.wem</Name></File><File><Name>jack_surprise3.wem</Name></File><File><Name>jack_surprise4.wem</Name></File><File><Name>jack_surprise5.wem</Name></File><File><Name>jack_surprise6.wem</Name></File><File><Name>jack_surprise7.wem</Name></File><File><Name>jack_surprise8.wem</Name></File><File><Name>jack_surprise9.wem</Name></File><File><Name>jack_surprisea.wem</Name></File><File><Name>jack_surpriseb.wem</Name></File><File><Name>jack_surprisec.wem</Name></File></FilesList></Path><Path><StateList><State><Name>PlaneStatus</Name><Value>Destroy</Value></State><State><Name>Plane_Type</Name><Value>Fighter</Value></State></StateList><FilesList><File><Name>balloon_pop1.wem</Name></File><File><Name>balloon_pop2.wem</Name></File><File><Name>balloon_pop3.wem</Name></File><File><Name>balloon_pop4.wem</Name></File><File><Name>balloon_pop5.wem</Name></File><File><Name>balloon_pop6.wem</Name></File></FilesList></Path><Path><StateList><State><Name>PlaneStatus</Name><Value>Destroy</Value></State><State><Name>Plane_Type</Name><Value>FighterCons</Value></State></StateList><FilesList><File><Name>zombie_entering_water.wem</Name></File></FilesList></Path><Path><StateList><State><Name>PlaneStatus</Name><Value>Destroy</Value></State><State><Name>Plane_Type</Name><Value>Scout</Value></State></StateList><FilesList><File><Name>zombie_entering_water.wem</Name></File></FilesList></Path><Path><StateList><State><Name>PlaneStatus</Name><Value>Destroy</Value></State><State><Name>Plane_Type</Name><Value>Torpedo</Value></State></StateList><FilesList><File><Name>balloon_pop1.wem</Name></File><File><Name>balloon_pop2.wem</Name></File><File><Name>balloon_pop3.wem</Name></File><File><Name>balloon_pop4.wem</Name></File><File><Name>balloon_pop5.wem</Name></File><File><Name>balloon_pop6.wem</Name></File></FilesList></Path><Path><StateList><State><Name>PlaneStatus</Name><Value>Engage</Value></State><State><Name>Plane_Type</Name><Value>Fighter</Value></State></StateList><FilesList><File><Name>newspaperrarrgh1.wem</Name></File><File><Name>newspaperrarrgh2.wem</Name></File><File><Name>newspaperrarrgh3.wem</Name></File><File><Name>newspaperrarrgh4.wem</Name></File><File><Name>newspaperrarrgh5.wem</Name></File><File><Name>newspaperrarrgh6.wem</Name></File><File><Name>newspaperrarrgh7.wem</Name></File><File><Name>newspaperrarrgh8.wem</Name></File><File><Name>newspaperrarrgh9.wem</Name></File><File><Name>newspaperrarrgha.wem</Name></File><File><Name>newspaperrarrghb.wem</Name></File><File><Name>newspaperrarrghc.wem</Name></File></FilesList></Path><Path><StateList><State><Name>PlaneStatus</Name><Value>Engage</Value></State><State><Name>Plane_Type</Name><Value>Torpedo</Value></State></StateList><FilesList><File><Name>newspaperrarrgh1.wem</Name></File><File><Name>newspaperrarrgh2.wem</Name></File><File><Name>newspaperrarrgh3.wem</Name></File><File><Name>newspaperrarrgh4.wem</Name></File><File><Name>newspaperrarrgh5.wem</Name></File><File><Name>newspaperrarrgh6.wem</Name></File><File><Name>newspaperrarrgh7.wem</Name></File><File><Name>newspaperrarrgh8.wem</Name></File><File><Name>newspaperrarrgh9.wem</Name></File><File><Name>newspaperrarrgha.wem</Name></File><File><Name>newspaperrarrghb.wem</Name></File><File><Name>newspaperrarrghc.wem</Name></File></FilesList></Path><Path><StateList><State><Name>Plane_Type</Name><Value>Fighter</Value></State><State><Name>PlaneStatus</Name><Value>Land</Value></State></StateList><FilesList><File><Name>gargantuar_thump1.wem</Name></File><File><Name>gargantuar_thump2.wem</Name></File><File><Name>gargantuar_thump3.wem</Name></File><File><Name>gargantuar_thump4.wem</Name></File><File><Name>gargantuar_thump5.wem</Name></File><File><Name>gargantuar_thump6.wem</Name></File></FilesList></Path><Path><StateList><State><Name>Plane_Type</Name><Value>Fighter</Value></State><State><Name>PlaneStatus</Name><Value>Ready</Value></State></StateList><FilesList><File><Name>ballooninflate1.wem</Name></File><File><Name>ballooninflate2.wem</Name></File><File><Name>ballooninflate3.wem</Name></File><File><Name>ballooninflate4.wem</Name></File><File><Name>ballooninflate5.wem</Name></File><File><Name>ballooninflate6.wem</Name></File></FilesList></Path><Path><StateList><State><Name>Plane_Type</Name><Value>Fighter</Value></State><State><Name>PlaneStatus</Name><Value>TangoDown</Value></State></StateList><FilesList><File><Name>Seagal_Speech_Pilots_Tangodown_1.wem</Name></File><File><Name>Seagal_Speech_Pilots_Tangodown_2.wem</Name></File></FilesList></Path><Path><StateList><State><Name>Plane_Type</Name><Value>Fighter</Value></State><State><Name>PlaneStatus</Name><Value>UnderAttack</Value></State></StateList><FilesList><File><Name>jack_surprise1.wem</Name></File><File><Name>jack_surprise2.wem</Name></File><File><Name>jack_surprise3.wem</Name></File><File><Name>jack_surprise4.wem</Name></File><File><Name>jack_surprise5.wem</Name></File><File><Name>jack_surprise6.wem</Name></File><File><Name>jack_surprise7.wem</Name></File><File><Name>jack_surprise8.wem</Name></File><File><Name>jack_surprise9.wem</Name></File><File><Name>jack_surprisea.wem</Name></File><File><Name>jack_surpriseb.wem</Name></File><File><Name>jack_surprisec.wem</Name></File></FilesList></Path><Path><StateList><State><Name>Plane_Type</Name><Value>FighterCons</Value></State><State><Name>PlaneStatus</Name><Value>Land</Value></State></StateList><FilesList><File><Name>crazydave1.wem</Name></File><File><Name>crazydave2.wem</Name></File><File><Name>crazydave3.wem</Name></File><File><Name>crazydave4.wem</Name></File><File><Name>crazydave5.wem</Name></File><File><Name>crazydave6.wem</Name></File><File><Name>crazydave7.wem</Name></File><File><Name>crazydave8.wem</Name></File><File><Name>crazydave9.wem</Name></File></FilesList></Path><Path><StateList><State><Name>PlaneStatus</Name><Value>Land</Value></State><State><Name>Plane_Type</Name><Value>Scout</Value></State></StateList><FilesList><File><Name>crazydave1.wem</Name></File><File><Name>crazydave2.wem</Name></File><File><Name>crazydave3.wem</Name></File><File><Name>crazydave4.wem</Name></File><File><Name>crazydave5.wem</Name></File><File><Name>crazydave6.wem</Name></File><File><Name>crazydave7.wem</Name></File><File><Name>crazydave8.wem</Name></File><File><Name>crazydave9.wem</Name></File></FilesList></Path><Path><StateList><State><Name>PlaneStatus</Name><Value>Land</Value></State><State><Name>Plane_Type</Name><Value>Torpedo</Value></State></StateList><FilesList><File><Name>gargantuar_thump1.wem</Name></File><File><Name>gargantuar_thump2.wem</Name></File><File><Name>gargantuar_thump3.wem</Name></File><File><Name>gargantuar_thump4.wem</Name></File><File><Name>gargantuar_thump5.wem</Name></File><File><Name>gargantuar_thump6.wem</Name></File></FilesList></Path><Path><StateList><State><Name>PlaneStatus</Name><Value>Ready</Value></State><State><Name>Plane_Type</Name><Value>Torpedo</Value></State></StateList><FilesList><File><Name>ballooninflate1.wem</Name></File><File><Name>ballooninflate2.wem</Name></File><File><Name>ballooninflate3.wem</Name></File><File><Name>ballooninflate4.wem</Name></File><File><Name>ballooninflate5.wem</Name></File><File><Name>ballooninflate6.wem</Name></File></FilesList></Path><Path><StateList><State><Name>PlaneStatus</Name><Value>TangoDown</Value></State><State><Name>Plane_Type</Name><Value>Torpedo</Value></State></StateList><FilesList><File><Name>bowlingimpact1.wem</Name></File><File><Name>bowlingimpact2.wem</Name></File><File><Name>bowlingimpact3.wem</Name></File><File><Name>bowlingimpact4.wem</Name></File><File><Name>bowlingimpact5.wem</Name></File><File><Name>bowlingimpact6.wem</Name></File><File><Name>bowlingimpact7.wem</Name></File><File><Name>bowlingimpact8.wem</Name></File><File><Name>bowlingimpact9.wem</Name></File><File><Name>bowlingimpacta.wem</Name></File><File><Name>bowlingimpactb.wem</Name></File><File><Name>bowlingimpactc.wem</Name></File></FilesList></Path><Path><StateList><State><Name>Plane_Type</Name><Value>Torpedo</Value></State><State><Name>PlaneStatus</Name><Value>UnderAttack</Value></State></StateList><FilesList><File><Name>jack_surprise1.wem</Name></File><File><Name>jack_surprise2.wem</Name></File><File><Name>jack_surprise3.wem</Name></File><File><Name>jack_surprise4.wem</Name></File><File><Name>jack_surprise5.wem</Name></File><File><Name>jack_surprise6.wem</Name></File><File><Name>jack_surprise7.wem</Name></File><File><Name>jack_surprise8.wem</Name></File><File><Name>jack_surprise9.wem</Name></File><File><Name>jack_surprisea.wem</Name></File><File><Name>jack_surpriseb.wem</Name></File><File><Name>jack_surprisec.wem</Name></File></FilesList></Path></Container></ExternalEvent><ExternalEvent><Name>Play_PriorityTarget</Name><Container><Name>Voice</Name><ExternalId>VPriorityTarget</ExternalId><Path><StateList></StateList><FilesList><File><Name>crazydave1.wem</Name></File><File><Name>crazydave2.wem</Name></File><File><Name>crazydave3.wem</Name></File><File><Name>crazydave4.wem</Name></File><File><Name>crazydave5.wem</Name></File><File><Name>crazydave6.wem</Name></File><File><Name>crazydave7.wem</Name></File><File><Name>crazydave8.wem</Name></File><File><Name>crazydave9.wem</Name></File></FilesList></Path></Container></ExternalEvent><ExternalEvent><Name>Play_quick_commands</Name><Container><Name>Voice</Name><ExternalId>Vquick_commands</ExternalId><Path><StateList><State><Name>quick_commands</Name><Value>CMD_QUICK_AYE_AYE</Value></State></StateList><FilesList><File><Name>crazydave1.wem</Name></File><File><Name>crazydave2.wem</Name></File><File><Name>crazydave3.wem</Name></File><File><Name>crazydave4.wem</Name></File><File><Name>crazydave5.wem</Name></File><File><Name>crazydave6.wem</Name></File><File><Name>crazydave7.wem</Name></File><File><Name>crazydave8.wem</Name></File><File><Name>crazydave9.wem</Name></File></FilesList></Path><Path><StateList><State><Name>quick_commands</Name><Value>CMD_QUICK_CARAMBA</Value></State></StateList><FilesList><File><Name>crazydaveE1.wem</Name></File><File><Name>crazydaveE2.wem</Name></File><File><Name>crazydaveE3.wem</Name></File></FilesList></Path><Path><StateList><State><Name>quick_commands</Name><Value>CMD_QUICK_GOOD_GAME</Value></State></StateList><FilesList><File><Name>crazydave1.wem</Name></File><File><Name>crazydave2.wem</Name></File><File><Name>crazydave3.wem</Name></File><File><Name>crazydave4.wem</Name></File><File><Name>crazydave5.wem</Name></File><File><Name>crazydave6.wem</Name></File><File><Name>crazydave7.wem</Name></File><File><Name>crazydave8.wem</Name></File><File><Name>crazydave9.wem</Name></File></FilesList></Path><Path><StateList><State><Name>quick_commands</Name><Value>CMD_QUICK_GOOD_LUCK</Value></State></StateList><FilesList><File><Name>crazydave1.wem</Name></File><File><Name>crazydave2.wem</Name></File><File><Name>crazydave3.wem</Name></File><File><Name>crazydave4.wem</Name></File><File><Name>crazydave5.wem</Name></File><File><Name>crazydave6.wem</Name></File><File><Name>crazydave7.wem</Name></File><File><Name>crazydave8.wem</Name></File><File><Name>crazydave9.wem</Name></File></FilesList></Path><Path><StateList><State><Name>quick_commands</Name><Value>CMD_QUICK_NEED_SUPPORT</Value></State></StateList><FilesList><File><Name>crazydaveE1.wem</Name></File><File><Name>crazydaveE2.wem</Name></File><File><Name>crazydaveE3.wem</Name></File></FilesList></Path><Path><StateList><State><Name>quick_commands</Name><Value>CMD_QUICK_NO_WAY</Value></State></StateList><FilesList><File><Name>crazydave1.wem</Name></File><File><Name>crazydave2.wem</Name></File><File><Name>crazydave3.wem</Name></File><File><Name>crazydave4.wem</Name></File><File><Name>crazydave5.wem</Name></File><File><Name>crazydave6.wem</Name></File><File><Name>crazydave7.wem</Name></File><File><Name>crazydave8.wem</Name></File><File><Name>crazydave9.wem</Name></File></FilesList></Path><Path><StateList><State><Name>quick_commands</Name><Value>CMD_QUICK_SOS</Value></State></StateList><FilesList><File><Name>crazydaveE1.wem</Name></File><File><Name>crazydaveE2.wem</Name></File><File><Name>crazydaveE3.wem</Name></File></FilesList></Path><Path><StateList><State><Name>quick_commands</Name><Value>CMD_QUICK_TACTIC_ALLY_BASE</Value></State></StateList><FilesList><File><Name>crazydave1.wem</Name></File><File><Name>crazydave2.wem</Name></File><File><Name>crazydave3.wem</Name></File><File><Name>crazydave4.wem</Name></File><File><Name>crazydave5.wem</Name></File><File><Name>crazydave6.wem</Name></File><File><Name>crazydave7.wem</Name></File><File><Name>crazydave8.wem</Name></File><File><Name>crazydave9.wem</Name></File></FilesList></Path><Path><StateList><State><Name>quick_commands</Name><Value>CMD_QUICK_TACTIC_ALLY_POINT</Value></State></StateList><FilesList><File><Name>crazydave1.wem</Name></File><File><Name>crazydave2.wem</Name></File><File><Name>crazydave3.wem</Name></File><File><Name>crazydave4.wem</Name></File><File><Name>crazydave5.wem</Name></File><File><Name>crazydave6.wem</Name></File><File><Name>crazydave7.wem</Name></File><File><Name>crazydave8.wem</Name></File><File><Name>crazydave9.wem</Name></File></FilesList></Path><Path><StateList><State><Name>quick_commands</Name><Value>CMD_QUICK_TACTIC_ALLY_SHIP</Value></State></StateList><FilesList><File><Name>crazydave1.wem</Name></File><File><Name>crazydave2.wem</Name></File><File><Name>crazydave3.wem</Name></File><File><Name>crazydave4.wem</Name></File><File><Name>crazydave5.wem</Name></File><File><Name>crazydave6.wem</Name></File><File><Name>crazydave7.wem</Name></File><File><Name>crazydave8.wem</Name></File><File><Name>crazydave9.wem</Name></File></FilesList></Path><Path><StateList><State><Name>quick_commands</Name><Value>CMD_QUICK_TACTIC_ENEMY_BASE</Value></State></StateList><FilesList><File><Name>crazydave1.wem</Name></File><File><Name>crazydave2.wem</Name></File><File><Name>crazydave3.wem</Name></File><File><Name>crazydave4.wem</Name></File><File><Name>crazydave5.wem</Name></File><File><Name>crazydave6.wem</Name></File><File><Name>crazydave7.wem</Name></File><File><Name>crazydave8.wem</Name></File><File><Name>crazydave9.wem</Name></File></FilesList></Path><Path><StateList><State><Name>quick_commands</Name><Value>CMD_QUICK_TACTIC_ENEMY_POINT</Value></State></StateList><FilesList><File><Name>crazydave1.wem</Name></File><File><Name>crazydave2.wem</Name></File><File><Name>crazydave3.wem</Name></File><File><Name>crazydave4.wem</Name></File><File><Name>crazydave5.wem</Name></File><File><Name>crazydave6.wem</Name></File><File><Name>crazydave7.wem</Name></File><File><Name>crazydave8.wem</Name></File><File><Name>crazydave9.wem</Name></File></FilesList></Path><Path><StateList><State><Name>quick_commands</Name><Value>CMD_QUICK_TACTIC_ENEMY_SHIP</Value></State></StateList><FilesList><File><Name>crazydave1.wem</Name></File><File><Name>crazydave2.wem</Name></File><File><Name>crazydave3.wem</Name></File><File><Name>crazydave4.wem</Name></File><File><Name>crazydave5.wem</Name></File><File><Name>crazydave6.wem</Name></File><File><Name>crazydave7.wem</Name></File><File><Name>crazydave8.wem</Name></File><File><Name>crazydave9.wem</Name></File></FilesList></Path><Path><StateList><State><Name>quick_commands</Name><Value>CMD_QUICK_THANK_YOU</Value></State></StateList><FilesList><File><Name>crazydave1.wem</Name></File><File><Name>crazydave2.wem</Name></File><File><Name>crazydave3.wem</Name></File><File><Name>crazydave4.wem</Name></File><File><Name>crazydave5.wem</Name></File><File><Name>crazydave6.wem</Name></File><File><Name>crazydave7.wem</Name></File><File><Name>crazydave8.wem</Name></File><File><Name>crazydave9.wem</Name></File></FilesList></Path><Path><StateList><State><Name>quick_commands</Name><Value>CMD_QUICK_NEED_AIR_DEFENCE</Value></State></StateList><FilesList><File><Name>crazydave1.wem</Name></File><File><Name>crazydave2.wem</Name></File><File><Name>crazydave3.wem</Name></File><File><Name>crazydave4.wem</Name></File><File><Name>crazydave5.wem</Name></File><File><Name>crazydave6.wem</Name></File><File><Name>crazydave7.wem</Name></File><File><Name>crazydave8.wem</Name></File><File><Name>crazydave9.wem</Name></File></FilesList></Path><Path><StateList><State><Name>quick_commands</Name><Value>CMD_QUICK_NEED_SUPPORT_ALLY_PLANE</Value></State></StateList><FilesList><File><Name>crazydave1.wem</Name></File><File><Name>crazydave2.wem</Name></File><File><Name>crazydave3.wem</Name></File><File><Name>crazydave4.wem</Name></File><File><Name>crazydave5.wem</Name></File><File><Name>crazydave6.wem</Name></File><File><Name>crazydave7.wem</Name></File><File><Name>crazydave8.wem</Name></File><File><Name>crazydave9.wem</Name></File></FilesList></Path><Path><StateList><State><Name>quick_commands</Name><Value>CMD_QUICK_TACTIC_ENEMY_BUILDING</Value></State></StateList><FilesList><File><Name>crazydaveE1.wem</Name></File><File><Name>crazydaveE2.wem</Name></File><File><Name>crazydaveE3.wem</Name></File></FilesList></Path><Path><StateList><State><Name>quick_commands</Name><Value>CMD_QUICK_TACTIC_ALLY_BUILDING</Value></State></StateList><FilesList><File><Name>crazydave1.wem</Name></File><File><Name>crazydave2.wem</Name></File><File><Name>crazydave3.wem</Name></File><File><Name>crazydave4.wem</Name></File><File><Name>crazydave5.wem</Name></File><File><Name>crazydave6.wem</Name></File><File><Name>crazydave7.wem</Name></File><File><Name>crazydave8.wem</Name></File><File><Name>crazydave9.wem</Name></File></FilesList></Path><Path><StateList><State><Name>quick_commands</Name><Value>CMD_QUICK_NEED_VISION</Value></State></StateList><FilesList><File><Name>crazydaveE1.wem</Name></File><File><Name>crazydaveE2.wem</Name></File><File><Name>crazydaveE3.wem</Name></File></FilesList></Path><Path><StateList><State><Name>quick_commands</Name><Value>CMD_QUICK_BACK_ALLY_SHIP</Value></State></StateList><FilesList><File><Name>crazydave1.wem</Name></File><File><Name>crazydave2.wem</Name></File><File><Name>crazydave3.wem</Name></File><File><Name>crazydave4.wem</Name></File><File><Name>crazydave5.wem</Name></File><File><Name>crazydave6.wem</Name></File><File><Name>crazydave7.wem</Name></File><File><Name>crazydave8.wem</Name></File><File><Name>crazydave9.wem</Name></File></FilesList></Path><Path><StateList><State><Name>quick_commands</Name><Value>CMD_QUICK_BACK</Value></State></StateList><FilesList><File><Name>crazydave1.wem</Name></File><File><Name>crazydave2.wem</Name></File><File><Name>crazydave3.wem</Name></File><File><Name>crazydave4.wem</Name></File><File><Name>crazydave5.wem</Name></File><File><Name>crazydave6.wem</Name></File><File><Name>crazydave7.wem</Name></File><File><Name>crazydave8.wem</Name></File><File><Name>crazydave9.wem</Name></File></FilesList></Path><Path><StateList><State><Name>quick_commands</Name><Value>CMD_QUICK_NEED_SMOKE</Value></State></StateList><FilesList><File><Name>Silence.wem</Name></File></FilesList></Path><Path><StateList><State><Name>quick_commands</Name><Value>CMD_QUICK_TACTIC_ALLY_PLANE</Value></State></StateList><FilesList><File><Name>Silence.wem</Name></File></FilesList></Path><Path><StateList><State><Name>quick_commands</Name><Value>CMD_QUICK_TACTIC_ENEMY_PLANE</Value></State></StateList><FilesList><File><Name>Silence.wem</Name></File></FilesList></Path><Path><StateList><State><Name>quick_commands</Name><Value>CMD_QUICK_THANK_YOU_ALLY_SHIP</Value></State></StateList><FilesList><File><Name>Silence.wem</Name></File></FilesList></Path><Path><StateList><State><Name>quick_commands</Name><Value>CMD_QUICK_NEED_SUPPORT_ALLY_SHIP</Value></State></StateList><FilesList><File><Name>Silence.wem</Name></File></FilesList></Path><Path><StateList><State><Name>quick_commands</Name><Value>CMD_QUICK_GOOD_GAME_ALLY_SHIP</Value></State></StateList><FilesList><File><Name>Silence.wem</Name></File></FilesList></Path></Container></ExternalEvent><ExternalEvent><Name>Play_quick_commands_receive</Name><Container><Name>Voice</Name><ExternalId>Vquick_commands_receive</ExternalId><Path><StateList><State><Name>quick_commands</Name><Value>CMD_QUICK_AYE_AYE</Value></State></StateList><FilesList><File><Name>crazydave1.wem</Name></File><File><Name>crazydave2.wem</Name></File><File><Name>crazydave3.wem</Name></File><File><Name>crazydave4.wem</Name></File><File><Name>crazydave5.wem</Name></File><File><Name>crazydave6.wem</Name></File><File><Name>crazydave7.wem</Name></File><File><Name>crazydave8.wem</Name></File><File><Name>crazydave9.wem</Name></File></FilesList></Path><Path><StateList><State><Name>quick_commands</Name><Value>CMD_QUICK_CARAMBA</Value></State></StateList><FilesList><File><Name>crazydaveE1.wem</Name></File><File><Name>crazydaveE2.wem</Name></File><File><Name>crazydaveE3.wem</Name></File></FilesList></Path><Path><StateList><State><Name>quick_commands</Name><Value>CMD_QUICK_GOOD_GAME</Value></State></StateList><FilesList><File><Name>crazydave1.wem</Name></File><File><Name>crazydave2.wem</Name></File><File><Name>crazydave3.wem</Name></File><File><Name>crazydave4.wem</Name></File><File><Name>crazydave5.wem</Name></File><File><Name>crazydave6.wem</Name></File><File><Name>crazydave7.wem</Name></File><File><Name>crazydave8.wem</Name></File><File><Name>crazydave9.wem</Name></File></FilesList></Path><Path><StateList><State><Name>quick_commands</Name><Value>CMD_QUICK_GOOD_LUCK</Value></State></StateList><FilesList><File><Name>crazydave1.wem</Name></File><File><Name>crazydave2.wem</Name></File><File><Name>crazydave3.wem</Name></File><File><Name>crazydave4.wem</Name></File><File><Name>crazydave5.wem</Name></File><File><Name>crazydave6.wem</Name></File><File><Name>crazydave7.wem</Name></File><File><Name>crazydave8.wem</Name></File><File><Name>crazydave9.wem</Name></File></FilesList></Path><Path><StateList><State><Name>quick_commands</Name><Value>CMD_QUICK_NEED_SUPPORT</Value></State></StateList><FilesList><File><Name>crazydave1.wem</Name></File><File><Name>crazydave2.wem</Name></File><File><Name>crazydave3.wem</Name></File><File><Name>crazydave4.wem</Name></File><File><Name>crazydave5.wem</Name></File><File><Name>crazydave6.wem</Name></File><File><Name>crazydave7.wem</Name></File><File><Name>crazydave8.wem</Name></File><File><Name>crazydave9.wem</Name></File></FilesList></Path><Path><StateList><State><Name>quick_commands</Name><Value>CMD_QUICK_NO_WAY</Value></State></StateList><FilesList><File><Name>crazydaveE1.wem</Name></File><File><Name>crazydaveE2.wem</Name></File><File><Name>crazydaveE3.wem</Name></File></FilesList></Path><Path><StateList><State><Name>quick_commands</Name><Value>CMD_QUICK_SOS</Value></State></StateList><FilesList><File><Name>crazydaveE1.wem</Name></File><File><Name>crazydaveE2.wem</Name></File><File><Name>crazydaveE3.wem</Name></File></FilesList></Path><Path><StateList><State><Name>quick_commands</Name><Value>CMD_QUICK_TACTIC_ALLY_BASE</Value></State></StateList><FilesList><File><Name>crazydave1.wem</Name></File><File><Name>crazydave2.wem</Name></File><File><Name>crazydave3.wem</Name></File><File><Name>crazydave4.wem</Name></File><File><Name>crazydave5.wem</Name></File><File><Name>crazydave6.wem</Name></File><File><Name>crazydave7.wem</Name></File><File><Name>crazydave8.wem</Name></File><File><Name>crazydave9.wem</Name></File></FilesList></Path><Path><StateList><State><Name>quick_commands</Name><Value>CMD_QUICK_TACTIC_ALLY_POINT</Value></State></StateList><FilesList><File><Name>crazydave1.wem</Name></File><File><Name>crazydave2.wem</Name></File><File><Name>crazydave3.wem</Name></File><File><Name>crazydave4.wem</Name></File><File><Name>crazydave5.wem</Name></File><File><Name>crazydave6.wem</Name></File><File><Name>crazydave7.wem</Name></File><File><Name>crazydave8.wem</Name></File><File><Name>crazydave9.wem</Name></File></FilesList></Path><Path><StateList><State><Name>quick_commands</Name><Value>CMD_QUICK_TACTIC_ALLY_SHIP</Value></State></StateList><FilesList><File><Name>crazydave1.wem</Name></File><File><Name>crazydave2.wem</Name></File><File><Name>crazydave3.wem</Name></File><File><Name>crazydave4.wem</Name></File><File><Name>crazydave5.wem</Name></File><File><Name>crazydave6.wem</Name></File><File><Name>crazydave7.wem</Name></File><File><Name>crazydave8.wem</Name></File><File><Name>crazydave9.wem</Name></File></FilesList></Path><Path><StateList><State><Name>quick_commands</Name><Value>CMD_QUICK_TACTIC_ENEMY_BASE</Value></State></StateList><FilesList><File><Name>crazydave1.wem</Name></File><File><Name>crazydave2.wem</Name></File><File><Name>crazydave3.wem</Name></File><File><Name>crazydave4.wem</Name></File><File><Name>crazydave5.wem</Name></File><File><Name>crazydave6.wem</Name></File><File><Name>crazydave7.wem</Name></File><File><Name>crazydave8.wem</Name></File><File><Name>crazydave9.wem</Name></File></FilesList></Path><Path><StateList><State><Name>quick_commands</Name><Value>CMD_QUICK_TACTIC_ENEMY_POINT</Value></State></StateList><FilesList><File><Name>crazydave1.wem</Name></File><File><Name>crazydave2.wem</Name></File><File><Name>crazydave3.wem</Name></File><File><Name>crazydave4.wem</Name></File><File><Name>crazydave5.wem</Name></File><File><Name>crazydave6.wem</Name></File><File><Name>crazydave7.wem</Name></File><File><Name>crazydave8.wem</Name></File><File><Name>crazydave9.wem</Name></File></FilesList></Path><Path><StateList><State><Name>quick_commands</Name><Value>CMD_QUICK_TACTIC_ENEMY_SHIP</Value></State></StateList><FilesList><File><Name>crazydave1.wem</Name></File><File><Name>crazydave2.wem</Name></File><File><Name>crazydave3.wem</Name></File><File><Name>crazydave4.wem</Name></File><File><Name>crazydave5.wem</Name></File><File><Name>crazydave6.wem</Name></File><File><Name>crazydave7.wem</Name></File><File><Name>crazydave8.wem</Name></File><File><Name>crazydave9.wem</Name></File></FilesList></Path><Path><StateList><State><Name>quick_commands</Name><Value>CMD_QUICK_THANK_YOU</Value></State></StateList><FilesList><File><Name>crazydave1.wem</Name></File><File><Name>crazydave2.wem</Name></File><File><Name>crazydave3.wem</Name></File><File><Name>crazydave4.wem</Name></File><File><Name>crazydave5.wem</Name></File><File><Name>crazydave6.wem</Name></File><File><Name>crazydave7.wem</Name></File><File><Name>crazydave8.wem</Name></File><File><Name>crazydave9.wem</Name></File></FilesList></Path><Path><StateList><State><Name>quick_commands</Name><Value>CMD_QUICK_NEED_AIR_DEFENCE</Value></State></StateList><FilesList><File><Name>Silence.wem</Name></File></FilesList></Path><Path><StateList><State><Name>quick_commands</Name><Value>CMD_QUICK_NEED_SUPPORT_ALLY_PLANE</Value></State></StateList><FilesList><File><Name>Silence.wem</Name></File></FilesList></Path><Path><StateList><State><Name>quick_commands</Name><Value>CMD_QUICK_TACTIC_ENEMY_BUILDING</Value></State></StateList><FilesList><File><Name>Silence.wem</Name></File></FilesList></Path><Path><StateList><State><Name>quick_commands</Name><Value>CMD_QUICK_TACTIC_ALLY_BUILDING</Value></State></StateList><FilesList><File><Name>Silence.wem</Name></File></FilesList></Path><Path><StateList><State><Name>quick_commands</Name><Value>CMD_QUICK_NEED_VISION</Value></State></StateList><FilesList><File><Name>Silence.wem</Name></File></FilesList></Path><Path><StateList><State><Name>quick_commands</Name><Value>CMD_QUICK_BACK_ALLY_SHIP</Value></State></StateList><FilesList><File><Name>Silence.wem</Name></File></FilesList></Path><Path><StateList><State><Name>quick_commands</Name><Value>CMD_QUICK_BACK</Value></State></StateList><FilesList><File><Name>Silence.wem</Name></File></FilesList></Path><Path><StateList><State><Name>quick_commands</Name><Value>CMD_QUICK_NEED_SMOKE</Value></State></StateList><FilesList><File><Name>Silence.wem</Name></File></FilesList></Path><Path><StateList><State><Name>quick_commands</Name><Value>CMD_QUICK_TACTIC_ALLY_PLANE</Value></State></StateList><FilesList><File><Name>Silence.wem</Name></File></FilesList></Path><Path><StateList><State><Name>quick_commands</Name><Value>CMD_QUICK_TACTIC_ENEMY_PLANE</Value></State></StateList><FilesList><File><Name>Silence.wem</Name></File></FilesList></Path><Path><StateList><State><Name>quick_commands</Name><Value>CMD_QUICK_THANK_YOU_ALLY_SHIP</Value></State></StateList><FilesList><File><Name>Silence.wem</Name></File></FilesList></Path><Path><StateList><State><Name>quick_commands</Name><Value>CMD_QUICK_NEED_SUPPORT_ALLY_SHIP</Value></State></StateList><FilesList><File><Name>Silence.wem</Name></File></FilesList></Path><Path><StateList><State><Name>quick_commands</Name><Value>CMD_QUICK_GOOD_GAME_ALLY_SHIP</Value></State></StateList><FilesList><File><Name>Silence.wem</Name></File></FilesList></Path></Container></ExternalEvent><ExternalEvent><Name>Play_Task_1</Name><Container><Name>Voice</Name><ExternalId>VTask_1</ExternalId><Path><StateList></StateList><FilesList><File><Name>crazydave1.wem</Name></File><File><Name>crazydave2.wem</Name></File><File><Name>crazydave3.wem</Name></File><File><Name>crazydave4.wem</Name></File><File><Name>crazydave5.wem</Name></File><File><Name>crazydave6.wem</Name></File><File><Name>crazydave7.wem</Name></File><File><Name>crazydave8.wem</Name></File><File><Name>crazydave9.wem</Name></File></FilesList></Path></Container></ExternalEvent><ExternalEvent><Name>Play_Task_2</Name><Container><Name>Voice</Name><ExternalId>VTask_2</ExternalId><Path><StateList></StateList><FilesList><File><Name>crazydave1.wem</Name></File><File><Name>crazydave2.wem</Name></File><File><Name>crazydave3.wem</Name></File><File><Name>crazydave4.wem</Name></File><File><Name>crazydave5.wem</Name></File><File><Name>crazydave6.wem</Name></File><File><Name>crazydave7.wem</Name></File><File><Name>crazydave8.wem</Name></File><File><Name>crazydave9.wem</Name></File></FilesList></Path></Container></ExternalEvent><ExternalEvent><Name>Play_Task_3</Name><Container><Name>Voice</Name><ExternalId>VTask_3</ExternalId><Path><StateList></StateList><FilesList><File><Name>Seagal_Speech_Tutorial_Task_3.wem</Name></File></FilesList></Path></Container></ExternalEvent><ExternalEvent><Name>Play_Task_4</Name><Container><Name>Voice</Name><ExternalId>VTask_4</ExternalId><Path><StateList></StateList><FilesList><File><Name>crazydave1.wem</Name></File><File><Name>crazydave2.wem</Name></File><File><Name>crazydave3.wem</Name></File><File><Name>crazydave4.wem</Name></File><File><Name>crazydave5.wem</Name></File><File><Name>crazydave6.wem</Name></File><File><Name>crazydave7.wem</Name></File><File><Name>crazydave8.wem</Name></File><File><Name>crazydave9.wem</Name></File></FilesList></Path></Container></ExternalEvent><ExternalEvent><Name>Play_Task_5</Name><Container><Name>Voice</Name><ExternalId>VTask_5</ExternalId><Path><StateList></StateList><FilesList><File><Name>crazydave1.wem</Name></File><File><Name>crazydave2.wem</Name></File><File><Name>crazydave3.wem</Name></File><File><Name>crazydave4.wem</Name></File><File><Name>crazydave5.wem</Name></File><File><Name>crazydave6.wem</Name></File><File><Name>crazydave7.wem</Name></File><File><Name>crazydave8.wem</Name></File><File><Name>crazydave9.wem</Name></File></FilesList></Path></Container></ExternalEvent><ExternalEvent><Name>Play_Task_6</Name><Container><Name>Voice</Name><ExternalId>VTask_6</ExternalId><Path><StateList></StateList><FilesList><File><Name>crazydave1.wem</Name></File><File><Name>crazydave2.wem</Name></File><File><Name>crazydave3.wem</Name></File><File><Name>crazydave4.wem</Name></File><File><Name>crazydave5.wem</Name></File><File><Name>crazydave6.wem</Name></File><File><Name>crazydave7.wem</Name></File><File><Name>crazydave8.wem</Name></File><File><Name>crazydave9.wem</Name></File></FilesList></Path></Container></ExternalEvent><ExternalEvent><Name>Play_Task_7</Name><Container><Name>Voice</Name><ExternalId>VTask_7</ExternalId><Path><StateList></StateList><FilesList><File><Name>crazydave1.wem</Name></File><File><Name>crazydave2.wem</Name></File><File><Name>crazydave3.wem</Name></File><File><Name>crazydave4.wem</Name></File><File><Name>crazydave5.wem</Name></File><File><Name>crazydave6.wem</Name></File><File><Name>crazydave7.wem</Name></File><File><Name>crazydave8.wem</Name></File><File><Name>crazydave9.wem</Name></File></FilesList></Path></Container></ExternalEvent><ExternalEvent><Name>Play_Task_8</Name><Container><Name>Voice</Name><ExternalId>VTask_8</ExternalId><Path><StateList></StateList><FilesList><File><Name>crazydave1.wem</Name></File><File><Name>crazydave2.wem</Name></File><File><Name>crazydave3.wem</Name></File><File><Name>crazydave4.wem</Name></File><File><Name>crazydave5.wem</Name></File><File><Name>crazydave6.wem</Name></File><File><Name>crazydave7.wem</Name></File><File><Name>crazydave8.wem</Name></File><File><Name>crazydave9.wem</Name></File></FilesList></Path></Container></ExternalEvent><ExternalEvent><Name>Play_Task_9</Name><Container><Name>Voice</Name><ExternalId>VTask_9</ExternalId><Path><StateList></StateList><FilesList><File><Name>crazydave1.wem</Name></File><File><Name>crazydave2.wem</Name></File><File><Name>crazydave3.wem</Name></File><File><Name>crazydave4.wem</Name></File><File><Name>crazydave5.wem</Name></File><File><Name>crazydave6.wem</Name></File><File><Name>crazydave7.wem</Name></File><File><Name>crazydave8.wem</Name></File><File><Name>crazydave9.wem</Name></File></FilesList></Path></Container></ExternalEvent><ExternalEvent><Name>Play_Teamkill_punishment</Name><Container><Name>Voice</Name><ExternalId>VTeamkill_punishment</ExternalId><Path><StateList></StateList><FilesList><File><Name>scream.wem</Name></File></FilesList></Path></Container></ExternalEvent><ExternalEvent><Name>Play_Timer5</Name><Container><Name>Voice</Name><ExternalId>VTimer5</ExternalId><Path><StateList></StateList><FilesList><File><Name>crazydave1.wem</Name></File><File><Name>crazydave2.wem</Name></File><File><Name>crazydave3.wem</Name></File><File><Name>crazydave4.wem</Name></File><File><Name>crazydave5.wem</Name></File><File><Name>crazydave6.wem</Name></File><File><Name>crazydave7.wem</Name></File><File><Name>crazydave8.wem</Name></File><File><Name>crazydave9.wem</Name></File></FilesList></Path></Container></ExternalEvent><ExternalEvent><Name>Play_Torpedo_Danger</Name><Container><Name>Voice</Name><ExternalId>VTorpedo_Danger</ExternalId><Path><StateList><State><Name>Torpedo_Location</Name><Value>Torpedo_Ahead</Value></State></StateList><FilesList><File><Name>dolphin_appears.wem</Name></File></FilesList></Path><Path><StateList><State><Name>Torpedo_Location</Name><Value>Torpedo_Back</Value></State></StateList><FilesList><File><Name>dolphin_appears.wem</Name></File></FilesList></Path><Path><StateList><State><Name>Torpedo_Location</Name><Value>Torpedo_Left</Value></State></StateList><FilesList><File><Name>dolphin_appears.wem</Name></File></FilesList></Path><Path><StateList><State><Name>Torpedo_Location</Name><Value>Torpedo_Right</Value></State></StateList><FilesList><File><Name>dolphin_appears.wem</Name></File></FilesList></Path></Container></ExternalEvent><ExternalEvent><Name>Play_UI_Defective_Modules</Name><Container><Name>Voice</Name><ExternalId>VUI_Defective_Modules</ExternalId><Path><StateList><State><Name>ModuleState</Name><Value>Crit</Value></State><State><Name>ModuleType</Name><Value>Engine</Value></State></StateList><FilesList><File><Name>yuck.wem</Name></File><File><Name>yuck2.wem</Name></File></FilesList></Path><Path><StateList><State><Name>ModuleState</Name><Value>Crit</Value></State><State><Name>ModuleType</Name><Value>MainGun</Value></State></StateList><FilesList><File><Name>yuck.wem</Name></File><File><Name>yuck2.wem</Name></File></FilesList></Path><Path><StateList><State><Name>ModuleState</Name><Value>Crit</Value></State><State><Name>ModuleType</Name><Value>StreeringWheel</Value></State></StateList><FilesList><File><Name>yuck.wem</Name></File><File><Name>yuck2.wem</Name></File></FilesList></Path><Path><StateList><State><Name>ModuleState</Name><Value>Dead</Value></State><State><Name>ModuleType</Name><Value>MainGun</Value></State></StateList><FilesList><File><Name>zombaquarium_die.wem</Name></File></FilesList></Path><Path><StateList><State><Name>ModuleState</Name><Value>Dead</Value></State><State><Name>ModuleType</Name><Value>TorpedoGun</Value></State></StateList><FilesList><File><Name>zombaquarium_die.wem</Name></File></FilesList></Path></Container></ExternalEvent></AudioModification></AudioModification.xml>